README.md
setup.py
python_sentinel.egg-info/PKG-INFO
python_sentinel.egg-info/SOURCES.txt
python_sentinel.egg-info/dependency_links.txt
python_sentinel.egg-info/entry_points.txt
python_sentinel.egg-info/not-zip-safe
python_sentinel.egg-info/requires.txt
python_sentinel.egg-info/top_level.txt
sentinel/__init__.py