Metadata-Version: 1.0
Name: python-sentinel
Version: 2019.5.28.1348
Summary: motion detection and alerts
Home-page: https://github.com/wdbm/sentinel
Author: Will Breaden Madden
Author-email: wbm@protonmail.ch
License: GPLv3
Platform: UNKNOWN
